README.rst
setup.cfg
setup.py
bise/__init__.py
bise.multilingualglossary.egg-info/PKG-INFO
bise.multilingualglossary.egg-info/SOURCES.txt
bise.multilingualglossary.egg-info/dependency_links.txt
bise.multilingualglossary.egg-info/entry_points.txt
bise.multilingualglossary.egg-info/namespace_packages.txt
bise.multilingualglossary.egg-info/not-zip-safe
bise.multilingualglossary.egg-info/paster_plugins.txt
bise.multilingualglossary.egg-info/requires.txt
bise.multilingualglossary.egg-info/top_level.txt
bise/multilingualglossary/__init__.py
bise/multilingualglossary/configure.zcml
bise/multilingualglossary/extender.py
bise/multilingualglossary/tests.py
bise/multilingualglossary/profiles/default/metadata.xml
docs/HISTORY.txt
docs/INSTALL.txt
docs/LICENSE.GPL
docs/LICENSE.txt