Metadata-Version: 1.1
Name: bise.multilingualglossary
Version: 1.0
Summary: Schema Extenders to add multilingual term and definitions to PloneGlossary
Home-page: https://github.com/eea/bise.multilingualglossary
Author: Mikel Larreategi
Author-email: mlarreategi@codesyntax.com
License: GPL
Platform: UNKNOWN
Classifier: Framework :: Plone
Classifier: Programming Language :: Python
